pymol_app/__init__.py
pymol_app/_app.py
pymol_app/_molfuncs.py
pymol_app-0.5.dist-info/entry_points.txt
pymol_app-0.5.dist-info/WHEEL
pymol_app-0.5.dist-info/METADATA
pymol_app-0.5.dist-info/RECORD
